xtalmet/__init__.py
xtalmet/crystal.py
xtalmet/distance.py
xtalmet/evaluator.py
xtalmet/py.typed
xtalmet/screen.py
xtalmet-0.1.0.dist-info/WHEEL
xtalmet-0.1.0.dist-info/METADATA
xtalmet-0.1.0.dist-info/RECORD
