Metadata-Version: 2.3
Name: xtalmet
Version: 0.1.0
Summary: Python package containing a variety of distance functions for crystals, as well as evaluation metrics for crystal generation.
Author: Masahiro Negishi
Author-email: Masahiro Negishi <m.negishi25@imperial.ac.uk>
License: MIT License
Requires-Dist: pymatgen>=2025.5.28
Requires-Dist: torch>=2.7.0
Requires-Dist: matminer>=0.9.3
Requires-Dist: average-minimum-distance>=1.5.3
Requires-Dist: smact>=3.1.0
Requires-Dist: mace-torch>=0.3.13
Requires-Dist: huggingface-hub
Requires-Python: >=3.12
Project-URL: Documentation, https://wmd-group.github.io/xtalmets/
Project-URL: Repository, https://github.com/WMD-group/xtalmet/
